{
  "environment": "web",
  "format": "html",
  "prefix": "https://storage.googleapis.com",
  "mainga": "UA-49880327-14",
  "updated": "2024-06-12T14:03:18-05:00",
  "id": "nombre-carpeta-codelab",
  "duration": 14,
  "title": "CodeLab de cómo crear un codelab usando markdown",
  "summary": "Resumen del codelab",
  "source": "markdown/example/example.md",
  "theme": "",
  "status": [
    "published"
  ],
  "category": [
    "iau",
    "codelab"
  ],
  "tags": [
    "web"
  ],
  "feedback": "https://github.com/ncarvajalc/codelabs-iau/issues",
  "url": "nombre-carpeta-codelab"
}
